<item><numero>1</numero><title>Premio de 29 millones en EuroMillones para un ganador en Palma de Mallorca</title><fecha></fecha><descripcion>En el sorteo de EuroMillones celebrado el pasado viernes, 2 de diciembre, el &uacute;nico acertante de primera categor&iacute;a se qued&oacute; en Espa&ntilde;a. El ganador gan&oacute; un premio de 29.377.167&euro;.<br />
El ganador, que valid&oacute; sus apuestas en el Despacho Receptor 61.015 de Palma de Mallorca (Illes Balears), participaba con dos apuestas para el sorteo del viernes, autom&aacute;ticas, por un importe de cinco euros.<br />
<br />
Adem&aacute;s, en este sorteo hubo otro acertante de 2&ordf; categor&iacute;a en nuestro pa&iacute;s. Un ganador de 565.854,24&euro; en Almer&iacute;a.&nbsp;</descripcion>\n</item><item><numero>2</numero><title>Euromillones: bote de 26.000.000€</title><fecha>Fri, 10 Dec 2021 22:18:57 +0100</fecha><descripcion>La jornada de Euromillones del pr&oacute;ximo 14 de diciembre de 2021 pone en juego un BOTE de 26.000.000&euro;.<br />
Juega ya Euromillones en loteriasyapuestas.es</descripcion>\n</item><item><numero>3</numero><title>Euromillones: premios y ganadores del 10 de diciembre de 2021</title><fecha>Fri, 10 Dec 2021 22:18:41 +0100</fecha><descripcion>En el sorteo de Euromillones del 10 de diciembre de 2021, la combinaci&oacute;n ganadora ha correspondido a los siguientes n&uacute;meros:<br />
11 - 21 - 33 - 38 - 42 Estrellas: 02 - 08Mill&oacute;n: VRV01377<br />
El reparto de premios queda como sigue:<br />
<br />
<br />
<br />
<br />
<br />
Categor&iacute;aAcertantesPremiosAcertantes Europa<br />
<br />
1&ordf; 5 + 2<br />
0<br />
0.00 &euro;<br />
0<br />
<br />
<br />
2&ordf; 5 + 1<br />
0<br />
702.913.65 &euro;<br />
1<br />
<br />
<br />
3&ordf; 5 + 0<br />
1<br />
18.253.61 &euro;<br />
9<br />
<br />
<br />
4&ordf; 4 + 2<br />
8<br />
1.003.33 &euro;<br />
51<br />
<br />
<br />
5&ordf; 4 + 1<br />
183<br />
109.86 &euro;<br />
858<br />
<br />
<br />
6&ordf; 3 + 2<br />
483<br />
41.24 &euro;<br />
2.416<br />
<br />
<br />
7&ordf; 4 + 0<br />
347<br />
37.49 &euro;<br />
1.868<br />
<br />
<br />
8&ordf; 2 + 2<br />
6.749<br />
10.20 &euro;<br />
34.309<br />
<br />
<br />
9&ordf; 3 + 1<br />
7.245<br />
10.79 &euro;<br />
36.195<br />
<br />
<br />
10&ordf; 3 + 0<br />
15.941<br />
9.27 &euro;<br />
78.448<br />
<br />
<br />
11&ordf; 1 + 2<br />
34.769<br />
4.97 &euro;<br />
177.263<br />
<br />
<br />
12&ordf; 2 + 1<br />
103.767<br />
5.42 &euro;<br />
511.808<br />
<br />
<br />
13&ordf; 2 + 0<br />
232.009<br />
4.01 &euro;<br />
1.114.785<br />
<br />
<br />
<br />
<br />
<br />
<br />
<br />
<br />
<br />
El Mill&oacute;nAcertantesPremio<br />
<br />
Ganador<br />
1<br />
1.000.000,00 &euro;<br />
<br />
<br />
<br />
<br />
<br />
<br />
Toda la informaci&oacute;n oficial sobre este sorteo de Euromillones</descripcion>\n</item><item><numero>4</numero><title>Euromillones: resultados del 10 de diciembre de 2021</title><fecha>Fri, 10 Dec 2021 21:30:17 +0100</fecha><descripcion>En el sorteo de Euromillones del 10 de diciembre de 2021, la combinaci&oacute;n ganadora ha correspondido a los siguientes n&uacute;meros:<br />
11 - 21 - 33 - 38 - 42 Estrellas: 02 - 08Mill&oacute;n: VRV01377<br />
Toda la informaci&oacute;n oficial sobre este sorteo de Euromillones</descripcion>\n</item><item><numero>5</numero><title>Euromillones: bote de 17.000.000€</title><fecha>Tue, 07 Dec 2021 22:20:34 +0100</fecha><descripcion>La jornada de Euromillones del pr&oacute;ximo 10 de diciembre de 2021 pone en juego un BOTE de 17.000.000&euro;.<br />
Juega ya Euromillones en loteriasyapuestas.es</descripcion>\n</item><item><numero>6</numero><title>Euromillones: premios y ganadores del 07 de diciembre de 2021</title><fecha>Tue, 07 Dec 2021 22:20:18 +0100</fecha><descripcion>En el sorteo de Euromillones del 07 de diciembre de 2021, la combinaci&oacute;n ganadora ha correspondido a los siguientes n&uacute;meros:<br />
22 - 31 - 38 - 46 - 47 Estrellas: 07 - 11Mill&oacute;n: VPB51633<br />
El reparto de premios queda como sigue:<br />
<br />
<br />
<br />
<br />
<br />
Categor&iacute;aAcertantesPremiosAcertantes Europa<br />
<br />
1&ordf; 5 + 2<br />
1<br />
143.469.842.00 &euro;<br />
1<br />
<br />
<br />
2&ordf; 5 + 1<br />
1<br />
418.527.23 &euro;<br />
2<br />
<br />
<br />
3&ordf; 5 + 0<br />
0<br />
24.454.18 &euro;<br />
8<br />
<br />
<br />
4&ordf; 4 + 2<br />
7<br />
1.603.55 &euro;<br />
38<br />
<br />
<br />
5&ordf; 4 + 1<br />
132<br />
150.87 &euro;<br />
744<br />
<br />
<br />
6&ordf; 3 + 2<br />
309<br />
71.23 &euro;<br />
1.666<br />
<br />
<br />
7&ordf; 4 + 0<br />
297<br />
52.25 &euro;<br />
1.596<br />
<br />
<br />
8&ordf; 2 + 2<br />
4.650<br />
15.98 &euro;<br />
26.098<br />
<br />
<br />
9&ordf; 3 + 1<br />
6.525<br />
12.91 &euro;<br />
36.010<br />
<br />
<br />
10&ordf; 3 + 0<br />
13.957<br />
11.17 &euro;<br />
77.524<br />
<br />
<br />
11&ordf; 1 + 2<br />
27.394<br />
7.13 &euro;<br />
147.002<br />
<br />
<br />
12&ordf; 2 + 1<br />
101.138<br />
6.18 &euro;<br />
534.527<br />
<br />
<br />
13&ordf; 2 + 0<br />
213.863<br />
4.60 &euro;<br />
1.156.075<br />
<br />
<br />
<br />
<br />
<br />
<br />
<br />
<br />
<br />
El Mill&oacute;nAcertantesPremio<br />
<br />
Ganador<br />
1<br />
1.000.000,00 &euro;<br />
<br />
<br />
<br />
<br />
<br />
<br />
Toda la informaci&oacute;n oficial sobre este sorteo de Euromillones</descripcion>\n</item><item><numero>7</numero><title>Euromillones: resultados del 07 de diciembre de 2021</title><fecha>Tue, 07 Dec 2021 21:30:18 +0100</fecha><descripcion>En el sorteo de Euromillones del 07 de diciembre de 2021, la combinaci&oacute;n ganadora ha correspondido a los siguientes n&uacute;meros:<br />
22 - 31 - 38 - 46 - 47 Estrellas: 07 - 11Mill&oacute;n: VPB51633<br />
Toda la informaci&oacute;n oficial sobre este sorteo de Euromillones</descripcion>\n</item><item><numero>8</numero><title>Euromillones: bote de 143.000.000€</title><fecha>Fri, 03 Dec 2021 22:25:40 +0100</fecha><descripcion>La jornada de Euromillones del pr&oacute;ximo 07 de diciembre de 2021 pone en juego un BOTE de 143.000.000&euro;.<br />
Juega ya Euromillones en loteriasyapuestas.es</descripcion>\n</item><item><numero>9</numero><title>Euromillones: premios y ganadores del 03 de diciembre de 2021</title><fecha>Fri, 03 Dec 2021 22:25:18 +0100</fecha><descripcion>En el sorteo de Euromillones del 03 de diciembre de 2021, la combinaci&oacute;n ganadora ha correspondido a los siguientes n&uacute;meros:<br />
21 - 22 - 29 - 32 - 46 Estrellas: 09 - 10Mill&oacute;n: VLG79327<br />
El reparto de premios queda como sigue:<br />
<br />
<br />
<br />
<br />
<br />
Categor&iacute;aAcertantesPremiosAcertantes Europa<br />
<br />
1&ordf; 5 + 2<br />
0<br />
0.00 &euro;<br />
0<br />
<br />
<br />
2&ordf; 5 + 1<br />
2<br />
197.329.29 &euro;<br />
6<br />
<br />
<br />
3&ordf; 5 + 0<br />
2<br />
30.746.07 &euro;<br />
9<br />
<br />
<br />
4&ordf; 4 + 2<br />
7<br />
1.915.33 &euro;<br />
45<br />
<br />
<br />
5&ordf; 4 + 1<br />
215<br />
154.30 &euro;<br />
1.029<br />
<br />
<br />
6&ordf; 3 + 2<br />
446<br />
80.12 &euro;<br />
2.095<br />
<br />
<br />
7&ordf; 4 + 0<br />
490<br />
49.12 &euro;<br />
2.401<br />
<br />
<br />
8&ordf; 2 + 2<br />
6.334<br />
18.85 &euro;<br />
31.282<br />
<br />
<br />
9&ordf; 3 + 1<br />
9.945<br />
12.93 &euro;<br />
50.869<br />
<br />
<br />
10&ordf; 3 + 0<br />
21.865<br />
10.47 &euro;<br />
116.931<br />
<br />
<br />
11&ordf; 1 + 2<br />
33.475<br />
8.83 &euro;<br />
168.029<br />
<br />
<br />
12&ordf; 2 + 1<br />
150.194<br />
6.03 &euro;<br />
774.721<br />
<br />
<br />
13&ordf; 2 + 0<br />
346.522<br />
4.14 &euro;<br />
1.816.954<br />
<br />
<br />
<br />
<br />
<br />
<br />
<br />
<br />
<br />
El Mill&oacute;nAcertantesPremio<br />
<br />
Ganador<br />
1<br />
1.000.000,00 &euro;<br />
<br />
<br />
<br />
<br />
<br />
<br />
Toda la informaci&oacute;n oficial sobre este sorteo de Euromillones</descripcion>\n</item><item><numero>10</numero><title>Euromillones: resultados del 03 de diciembre de 2021</title><fecha>Fri, 03 Dec 2021 21:42:16 +0100</fecha><descripcion>En el sorteo de Euromillones del 03 de diciembre de 2021, la combinaci&oacute;n ganadora ha correspondido a los siguientes n&uacute;meros:<br />
21 - 22 - 29 - 32 - 46 Estrellas: 09 - 10Mill&oacute;n: VLG79327<br />
Toda la informaci&oacute;n oficial sobre este sorteo de Euromillones</descripcion>\n</item><item><numero>11</numero><title>Euromillones: bote de 130.000.000€</title><fecha>Tue, 30 Nov 2021 22:20:13 +0100</fecha><descripcion>La jornada de Euromillones del pr&oacute;ximo 03 de diciembre de 2021 pone en juego un BOTE de 130.000.000&euro;.<br />
Juega ya Euromillones en loteriasyapuestas.es</descripcion>\n</item><item><numero>12</numero><title>Euromillones: premios y ganadores del 30 de noviembre de 2021</title><fecha>Tue, 30 Nov 2021 22:19:57 +0100</fecha><descripcion>En el sorteo de Euromillones del 30 de noviembre de 2021, la combinaci&oacute;n ganadora ha correspondido a los siguientes n&uacute;meros:<br />
19 - 20 - 26 - 33 - 43 Estrellas: 01 - 04Mill&oacute;n: VKQ88775<br />
El reparto de premios queda como sigue:<br />
<br />
<br />
<br />
<br />
<br />
Categor&iacute;aAcertantesPremiosAcertantes Europa<br />
<br />
1&ordf; 5 + 2<br />
0<br />
0.00 &euro;<br />
0<br />
<br />
<br />
2&ordf; 5 + 1<br />
1<br />
523.711.83 &euro;<br />
1<br />
<br />
<br />
3&ordf; 5 + 0<br />
2<br />
40.800.03 &euro;<br />
3<br />
<br />
<br />
4&ordf; 4 + 2<br />
5<br />
1.657.59 &euro;<br />
23<br />
<br />
<br />
5&ordf; 4 + 1<br />
92<br />
142.45 &euro;<br />
493<br />
<br />
<br />
6&ordf; 3 + 2<br />
219<br />
70.77 &euro;<br />
1.049<br />
<br />
<br />
7&ordf; 4 + 0<br />
236<br />
47.21 &euro;<br />
1.105<br />
<br />
<br />
8&ordf; 2 + 2<br />
3.502<br />
16.30 &euro;<br />
16.002<br />
<br />
<br />
9&ordf; 3 + 1<br />
4.901<br />
12.63 &euro;<br />
23.029<br />
<br />
<br />
10&ordf; 3 + 0<br />
11.863<br />
10.10 &euro;<br />
53.637<br />
<br />
<br />
11&ordf; 1 + 2<br />
18.499<br />
7.57 &euro;<br />
86.639<br />
<br />
<br />
12&ordf; 2 + 1<br />
75.004<br />
5.86 &euro;<br />
352.475<br />
<br />
<br />
13&ordf; 2 + 0<br />
184.041<br />
4.03 &euro;<br />
826.573<br />
<br />
<br />
<br />
<br />
<br />
<br />
<br />
<br />
<br />
El Mill&oacute;nAcertantesPremio<br />
<br />
Ganador<br />
1<br />
1.000.000,00 &euro;<br />
<br />
<br />
<br />
<br />
<br />
<br />
Toda la informaci&oacute;n oficial sobre este sorteo de Euromillones</descripcion>\n</item><item><numero>13</numero><title>Euromillones: resultados del 30 de noviembre de 2021</title><fecha>Tue, 30 Nov 2021 21:30:18 +0100</fecha><descripcion>En el sorteo de Euromillones del 30 de noviembre de 2021, la combinaci&oacute;n ganadora ha correspondido a los siguientes n&uacute;meros:<br />
19 - 20 - 26 - 33 - 43 Estrellas: 01 - 04Mill&oacute;n: VKQ88775<br />
Toda la informaci&oacute;n oficial sobre este sorteo de Euromillones</descripcion>\n</item><item><numero>14</numero><title>Euromillones: bote de 17.000.000€</title><fecha>Fri, 26 Nov 2021 21:58:38 +0100</fecha><descripcion>La jornada de Euromillones del pr&oacute;ximo 30 de noviembre de 2021 pone en juego un BOTE de 17.000.000&euro;.<br />
Juega ya Euromillones en loteriasyapuestas.es</descripcion>\n</item><item><numero>15</numero><title>Euromillones: premios y ganadores del 26 de noviembre de 2021</title><fecha>Fri, 26 Nov 2021 21:58:22 +0100</fecha><descripcion>En el sorteo de Euromillones del 26 de noviembre de 2021, la combinaci&oacute;n ganadora ha correspondido a los siguientes n&uacute;meros:<br />
01 - 20 - 41 - 42 - 50 Estrellas: 03 - 07Mill&oacute;n: VGR04961<br />
El reparto de premios queda como sigue:<br />
<br />
<br />
<br />
<br />
<br />
Categor&iacute;aAcertantesPremiosAcertantes Europa<br />
<br />
1&ordf; 5 + 2<br />
0<br />
162.289.050.00 &euro;<br />
1<br />
<br />
<br />
2&ordf; 5 + 1<br />
2<br />
152.675.69 &euro;<br />
7<br />
<br />
<br />
3&ordf; 5 + 0<br />
2<br />
35.682.82 &euro;<br />
7<br />
<br />
<br />
4&ordf; 4 + 2<br />
7<br />
1.852.39 &euro;<br />
42<br />
<br />
<br />
5&ordf; 4 + 1<br />
171<br />
154.60 &euro;<br />
927<br />
<br />
<br />
6&ordf; 3 + 2<br />
480<br />
62.87 &euro;<br />
2.410<br />
<br />
<br />
7&ordf; 4 + 0<br />
409<br />
52.21 &euro;<br />
2.039<br />
<br />
<br />
8&ordf; 2 + 2<br />
8.668<br />
12.32 &euro;<br />
43.207<br />
<br />
<br />
9&ordf; 3 + 1<br />
8.413<br />
13.78 &euro;<br />
43.094<br />
<br />
<br />
10&ordf; 3 + 0<br />
18.814<br />
11.52 &euro;<br />
95.975<br />
<br />
<br />
11&ordf; 1 + 2<br />
56.312<br />
4.80 &euro;<br />
279.019<br />
<br />
<br />
12&ordf; 2 + 1<br />
135.834<br />
6.16 &euro;<br />
684.207<br />
<br />
<br />
13&ordf; 2 + 0<br />
287.311<br />
4.65 &euro;<br />
1.461.450<br />
<br />
<br />
<br />
<br />
<br />
<br />
<br />
<br />
<br />
El Mill&oacute;nAcertantesPremio<br />
<br />
Ganador<br />
1<br />
1.000.000,00 &euro;<br />
<br />
<br />
<br />
<br />
<br />
<br />
Toda la informaci&oacute;n oficial sobre este sorteo de Euromillones</descripcion>\n</item><item><numero>16</numero><title>Euromillones: resultados del 26 de noviembre de 2021</title><fecha>Fri, 26 Nov 2021 21:30:21 +0100</fecha><descripcion>En el sorteo de Euromillones del 26 de noviembre de 2021, la combinaci&oacute;n ganadora ha correspondido a los siguientes n&uacute;meros:<br />
01 - 20 - 41 - 42 - 50 Estrellas: 03 - 07Mill&oacute;n: VGR04961<br />
Toda la informaci&oacute;n oficial sobre este sorteo de Euromillones</descripcion>\n</item><item><numero>17</numero><title>Euromillones: bote de 163.000.000€</title><fecha>Tue, 23 Nov 2021 21:58:26 +0100</fecha><descripcion>La jornada de Euromillones del pr&oacute;ximo 26 de noviembre de 2021 pone en juego un BOTE de 163.000.000&euro;.<br />
Juega ya Euromillones en loteriasyapuestas.es</descripcion>\n</item><item><numero>18</numero><title>Euromillones: premios y ganadores del 23 de noviembre de 2021</title><fecha>Tue, 23 Nov 2021 21:58:10 +0100</fecha><descripcion>En el sorteo de Euromillones del 23 de noviembre de 2021, la combinaci&oacute;n ganadora ha correspondido a los siguientes n&uacute;meros:<br />
17 - 21 - 36 - 42 - 46 Estrellas: 07 - 10Mill&oacute;n: VBS54947<br />
El reparto de premios queda como sigue:<br />
<br />
<br />
<br />
<br />
<br />
Categor&iacute;aAcertantesPremiosAcertantes Europa<br />
<br />
1&ordf; 5 + 2<br />
0<br />
0.00 &euro;<br />
0<br />
<br />
<br />
2&ordf; 5 + 1<br />
0<br />
397.120.97 &euro;<br />
2<br />
<br />
<br />
3&ordf; 5 + 0<br />
3<br />
23.203.43 &euro;<br />
8<br />
<br />
<br />
4&ordf; 4 + 2<br />
12<br />
1.445.46 &euro;<br />
40<br />
<br />
<br />
5&ordf; 4 + 1<br />
183<br />
128.17 &euro;<br />
831<br />
<br />
<br />
6&ordf; 3 + 2<br />
394<br />
62.69 &euro;<br />
1.796<br />
<br />
<br />
7&ordf; 4 + 0<br />
396<br />
43.50 &euro;<br />
1.819<br />
<br />
<br />
8&ordf; 2 + 2<br />
5.518<br />
15.41 &euro;<br />
25.664<br />
<br />
<br />
9&ordf; 3 + 1<br />
7.927<br />
12.20 &euro;<br />
36.160<br />
<br />
<br />
10&ordf; 3 + 0<br />
16.836<br />
10.46 &euro;<br />
78.528<br />
<br />
<br />
11&ordf; 1 + 2<br />
29.707<br />
7.01 &euro;<br />
141.863<br />
<br />
<br />
12&ordf; 2 + 1<br />
112.324<br />
5.86 &euro;<br />
534.870<br />
<br />
<br />
13&ordf; 2 + 0<br />
236.748<br />
4.31 &euro;<br />
1.170.306<br />
<br />
<br />
<br />
<br />
<br />
<br />
<br />
<br />
<br />
El Mill&oacute;nAcertantesPremio<br />
<br />
Ganador<br />
1<br />
1.000.000,00 &euro;<br />
<br />
<br />
<br />
<br />
<br />
<br />
Toda la informaci&oacute;n oficial sobre este sorteo de Euromillones</descripcion>\n</item><item><numero>19</numero><title>Euromillones: resultados del 23 de noviembre de 2021</title><fecha>Tue, 23 Nov 2021 21:30:18 +0100</fecha><descripcion>En el sorteo de Euromillones del 23 de noviembre de 2021, la combinaci&oacute;n ganadora ha correspondido a los siguientes n&uacute;meros:<br />
17 - 21 - 36 - 42 - 46 Estrellas: 07 - 10Mill&oacute;n: VBS54947<br />
Toda la informaci&oacute;n oficial sobre este sorteo de Euromillones</descripcion>\n</item><item><numero>20</numero><title>Euromillones: bote de 145.000.000€</title><fecha>Fri, 19 Nov 2021 22:20:38 +0100</fecha><descripcion>La jornada de Euromillones del pr&oacute;ximo 23 de noviembre de 2021 pone en juego un BOTE de 145.000.000&euro;.<br />
Juega ya Euromillones en loteriasyapuestas.es</descripcion>\n</item>